overrides/__init__.py
overrides/enforce.py
overrides/final.py
overrides/overrides.py
overrides/py.typed
overrides/signature.py
overrides/typing_utils.py
overrides-7.6.0.dist-info/LICENSE
overrides-7.6.0.dist-info/METADATA
overrides-7.6.0.dist-info/WHEEL
overrides-7.6.0.dist-info/top_level.txt
overrides-7.6.0.dist-info/RECORD
