Metadata-Version: 2.1
Name: overrides
Version: 7.6.0
Summary: A decorator to automatically detect mismatch when overriding a method.
Home-page: https://github.com/mkorpela/overrides
Author: Mikko Korpela
Author-email: mikko.korpela@gmail.com
License: Apache License, Version 2.0
Keywords: override,inheritence,OOP
Classifier: Intended Audience :: Developers
Classifier: Programming Language :: Python :: 3.6
Classifier: Programming Language :: Python :: 3.7
Classifier: Programming Language :: Python :: 3.8
Classifier: Programming Language :: Python :: 3.9
Requires-Python: >=3.6
License-File: LICENSE
